[
  {
    "id": "stream-2026-06-12",
    "title": "【深夜歌雜】別急著站起來，偶爾跌倒後躺著看天空也不錯　░  歌枠｜Singing Stream #shorts",
    "date": "2026-06-12",
    "videoId": "WTPx_GgMKs8",
    "youtubeUrl": "https://www.youtube.com/watch?v=WTPx_GgMKs8"
  },
  {
    "id": "stream-2026-06-08",
    "title": "【伴睡歌回】是不是連放鬆的時候，腦袋裡還在責怪自己。自分を責めるの、少し休みませんか？　░ 睡眠導入歌枠｜Singing Stream",
    "date": "2026-06-08",
    "videoId": "6S3gCcIE4K4",
    "youtubeUrl": "https://www.youtube.com/watch?v=6S3gCcIE4K4",
    "credit": {
      "author": "@a2681a",
      "commentUrl": "https://www.youtube.com/watch?v=6S3gCcIE4K4&lc=UgwJl0pkrLVHzdpWSjB4AaABAg"
    }
  },
  {
    "id": "stream-bc303791",
    "title": "【突發歌雜】不想讓腦袋的聲音充斥安靜的夜晚，那來聽聽歌吧　░ 睡眠導入歌枠｜Singing Stream #shorts",
    "date": "2026-06-03",
    "videoId": "KB2cNRbeaKc",
    "youtubeUrl": "https://www.youtube.com/watch?v=KB2cNRbeaKc",
    "credit": {
      "author": "@a2681a",
      "commentUrl": "https://www.youtube.com/watch?v=KB2cNRbeaKc&lc=Ugy8LRXi6U09MNbrizJ4AaABAg"
    }
  },
  {
    "id": "stream-2026-04-06",
    "title": "【伴睡歌回】那些真心付出過的，不是錯過了什麼，而是你曾經很用力在喜歡。本気で想っていた気持ちは、何かを失ったわけじゃなくて、ただ好きだった証だ。░ 睡眠導入歌枠｜Singing Stream",
    "date": "2026-04-06",
    "videoId": "zlRzb3iDgn4",
    "youtubeUrl": "https://www.youtube.com/watch?v=zlRzb3iDgn4"
  },
  {
    "id": "stream-2026-04-03",
    "title": "【倫家想唱歌】練習唱唱歌！想把開心帶給你們！辛苦惹你這次連假要做甚麼呢  ░ 歌枠｜Singing Stream",
    "date": "2026-04-03",
    "videoId": "KzjBXLsjzU4",
    "youtubeUrl": "https://www.youtube.com/watch?v=KzjBXLsjzU4"
  },
  {
    "id": "stream-2026-03-30",
    "title": "【伴睡歌回】當世界開始讓你懷疑自己的時候，是不是又在想，為什麼明明努力了卻好像只有自己跟不上。頑張ってるのに、自分だけ追いつけないって思うとき。░ 睡眠導入歌枠｜Singing Stream",
    "date": "2026-03-30",
    "videoId": "2iZkLT5vemI",
    "youtubeUrl": "https://www.youtube.com/watch?v=2iZkLT5vemI"
  },
  {
    "id": "stream-c85e01e7",
    "title": "【倫家想唱歌】來陪你惹!!!!!!!趁你午休偷偷唱歌偷偷聊天🤩🤩🤩 和玩玩看新東西!!! ░ 歌枠｜Singing Stream",
    "date": "2026-03-24",
    "videoId": "dJ4z3FliynU",
    "youtubeUrl": "https://www.youtube.com/watch?v=dJ4z3FliynU"
  },
  {
    "id": "stream-2026-03-16",
    "title": "【伴睡歌回】晚安 ░ 睡眠導入歌枠｜Singing Stream",
    "date": "2026-03-16",
    "videoId": "tqLA2FnNO84",
    "youtubeUrl": "https://www.youtube.com/watch?v=tqLA2FnNO84"
  },
  {
    "id": "stream-2026-03-09",
    "title": "【伴睡歌回】有些感受不是說不出口，是說了也不一定被懂。給還醒著的你：今晚輕輕唱陪你入睡。 言えないわけじゃない。でも、言っても伝わらないこともあるよね。░ 睡眠導入歌枠｜Singing Stream",
    "date": "2026-03-09",
    "videoId": "IVfl4IDi0co",
    "youtubeUrl": "https://www.youtube.com/watch?v=IVfl4IDi0co"
  },
  {
    "id": "stream-e5230a57",
    "title": "【倫家想唱歌】別想著明天，讓我們先開心地度過周日夜晚!!!!!!!!(先說不唱超跑了喔)  ░ 歌枠｜Singing Stream",
    "date": "2026-03-08",
    "videoId": "xQ5TCl3JnXs",
    "youtubeUrl": "https://www.youtube.com/watch?v=xQ5TCl3JnXs"
  },
  {
    "id": "stream-2022-09-19",
    "title": "【 寝落ち歌枠】聊著天唱著歌～突然就想睡了呢！【厄倫蒂兒 Earendel】",
    "date": "2022-09-19",
    "videoId": "71i2JN0e-xE",
    "youtubeUrl": "https://www.youtube.com/watch?v=71i2JN0e-xE",
    "credit": {
      "author": "@空沐銀月",
      "commentUrl": "https://www.youtube.com/watch?v=71i2JN0e-xE&lc=UgzkiKVmBrV5lCKk2fF4AaABAg"
    }
  },
  {
    "id": "stream-08cd4aad",
    "title": "【 寝落ち歌枠】睡前唱些輕柔的歌，再兩天就放假了加油！【厄倫蒂兒 Earendel】",
    "date": "2022-09-14",
    "videoId": "Fq2wuNB-E7c",
    "youtubeUrl": "https://www.youtube.com/watch?v=Fq2wuNB-E7c",
    "credit": {
      "author": "@桜の雪-m5x",
      "commentUrl": "https://www.youtube.com/watch?v=Fq2wuNB-E7c&lc=UgwQrtacGMrcIsDRM0h4AaABAg"
    }
  },
  {
    "id": "stream-8c4cf2a6",
    "title": "【 中秋歌回！】唱些與夏夜相關及棉花糖的點歌！【厄倫蒂兒 Earendel】",
    "date": "2022-09-10",
    "videoId": "hraT9N8sQI4",
    "youtubeUrl": "https://www.youtube.com/watch?v=hraT9N8sQI4",
    "credit": {
      "author": "@桜の雪-m5x",
      "commentUrl": "https://www.youtube.com/watch?v=hraT9N8sQI4&lc=UgyTgpv2aTL29q2N9zR4AaABAg"
    }
  },
  {
    "id": "stream-2022-09-05",
    "title": "【中文歌枠】粉絲名決定！星期一來點動力！【厄倫蒂兒 Earendel】",
    "date": "2022-09-05",
    "videoId": "EZtqMl9Vwa4",
    "youtubeUrl": "https://www.youtube.com/watch?v=EZtqMl9Vwa4"
  },
  {
    "id": "stream-0aab9bcf",
    "title": "【動畫歌枠+粉絲名決定！】唱唱那些年最喜歡的經典動畫歌【厄倫蒂兒 Earendel】",
    "date": "2022-09-04",
    "videoId": "NJ6jZdviv5M",
    "youtubeUrl": "https://www.youtube.com/watch?v=NJ6jZdviv5M",
    "credit": {
      "author": "@dd981",
      "commentUrl": "https://www.youtube.com/watch?v=NJ6jZdviv5M&lc=UgyXApEo0jaBnKWPJix4AaABAg"
    }
  },
  {
    "id": "stream-daaf4871",
    "title": "【歌枠】２次會💫輕鬆唱唱  【厄倫蒂兒．Vtuber】",
    "date": "2022-08-29",
    "videoId": "GsG6hS5bOsA",
    "youtubeUrl": "https://www.youtube.com/watch?v=GsG6hS5bOsA",
    "credit": {
      "author": "@丹尼店長",
      "commentUrl": "https://www.youtube.com/watch?v=GsG6hS5bOsA&lc=Ugwyq6mfR4Gt0wu6plh4AaABAg"
    }
  }
]
